{
  "required": true,
  "minVersion": "0.8",
  "package": "com.xinian.KryptonHybrid.mixin",
  "compatibilityLevel": "JAVA_21",
  "refmap": "krypton_hybrid.refmap.json",
  "mixins": [
    "fastchunkentityaccess.EntitySectionAccessor",
    "fastchunkentityaccess.EntitySectionStorageMixin",
    "fastchunkentityaccess.PersistentEntitySectionManagerAccessor",
    "fastchunkentityaccess.ServerLevelMixin",
    "network.avoidwork.ChunkMapAvoidWorkMixin",
    "network.avoidwork.ChunkMapTrackedEntityInvoker",
    "network.blockentity.ChunkHolderBlockEntityMixin",
    "network.blockentity.ServerGamePacketListenerDeltaMixin",
    "network.chunk.ChunkDataOptMixin",
    "network.chunk.ChunkLightCompressMixin",
    "network.chunk.ChunkMapDccMixin",
    "network.chunk.ClientboundLevelChunkWithLightPacketMixin",
    "network.chunk.ClientboundLightUpdatePacketMixin",
    "network.chunk.PlayerChunkSenderMixin",
    "network.flushconsolidation.ChunkHolderBroadcastMixin",
    "network.flushconsolidation.ChunkMapFlushMixin",
    "network.flushconsolidation.ConnectionMixin",
    "network.flushconsolidation.ServerChunkCacheBroadcastMixin",
    "network.flushconsolidation.ServerEntityFlushMixin",
    "network.flushconsolidation.TrackedEntityBundleMixin",
    "network.microopt.FriendlyByteBufMixin",
    "network.microopt.MoveEntityPacketAccessor",
    "network.microopt.RotateHeadPacketAccessor",
    "network.microopt.ServerEntityDataThrottleMixin",
    "network.microopt.ServerEntityMixin",
    "network.microopt.VarIntMixin",
    "network.microopt.VarLongMixin",
    "network.pipeline.IServerCommonListenerAccessor",
    "network.pipeline.LegacyQueryHandlerMixin",
    "network.pipeline.PacketEncoderMixin",
    "network.pipeline.Varint21FrameDecoderMixin",
    "network.pipeline.ServerConnectionListenerMixin",
    "network.pipeline.HandshakeValidatorMixin",
    "network.pipeline.ServerStatusPacketListenerImplMixin",
    "network.pipeline.LoginTimeoutAdvanceMixin",
    "network.pipeline.ConfigurationFinishPhaseMixin",
    "network.pipeline.ConnectionAccessor",
    "network.pipeline.compression.ConnectionMixin",
    "network.pipeline.encryption.ConnectionMixin",
    "network.pipeline.encryption.ServerLoginPacketListenerImplMixin"
  ],
  "client": [
    "fastchunkentityaccess.ClientLevelMixin",
    "fastchunkentityaccess.TransientEntitySectionManagerAccessor",
    "network.blockentity.ClientBlockEntityDeltaMixin"
  ],
  "injectors": {
    "defaultRequire": 1
  }
}
